crsmssql/__init__.py
crsmssql/crsmssql.py
crsmssql-1.0.6.dist-info/LICENSE
crsmssql-1.0.6.dist-info/METADATA
crsmssql-1.0.6.dist-info/WHEEL
crsmssql-1.0.6.dist-info/top_level.txt
crsmssql-1.0.6.dist-info/RECORD
