Metadata-Version: 2.1
Name: crsmssql
Version: 1.0.6
Summary: This is my personal toolkit.
Home-page: https://github.com/wsywddr
Author: Chris Chen
Author-email: wsywddr@163.com
License: UNKNOWN
Platform: UNKNOWN
Classifier: Programming Language :: Python :: 3
Classifier: License :: OSI Approved :: MIT License
Classifier: Operating System :: OS Independent
Requires-Dist: pymssql (==2.1.4)
